bvpTune/__init__.py
bvpTune/bvpTune.py
bvpTune/optimizer.py
bvpTune/train_classication_models.py
bvpTune/train_regression_models.py
bvpTune/visualizer.py
bvpTune-0.1.4.dist-info/METADATA
bvpTune-0.1.4.dist-info/WHEEL
bvpTune-0.1.4.dist-info/top_level.txt
bvpTune-0.1.4.dist-info/RECORD
