Metadata-Version: 2.1
Name: bvpTune
Version: 0.1.4
Summary: Library for fine tuning the numerical settings of boundary value problem solvers
Home-page: https://bvpTune.readthedocs.io/
Author: Viny Saajan Victor
Author-email: viny.saajan.victor@itwm.fraunhofer.de
License: MIT
Platform: UNKNOWN
Classifier: Intended Audience :: Developers
Classifier: License :: OSI Approved :: MIT License
Classifier: Programming Language :: Python
Classifier: Programming Language :: Python :: 3
Classifier: Programming Language :: Python :: 3.6
Classifier: Programming Language :: Python :: 3.7
Classifier: Programming Language :: Python :: 3.8
Classifier: Programming Language :: Python :: 3.9
Classifier: Operating System :: OS Independent
Requires-Dist: numpy
Requires-Dist: pandas
Requires-Dist: scikit-learn
Requires-Dist: lightgbm
Requires-Dist: catboost
Requires-Dist: keras
Requires-Dist: tensorflow
Requires-Dist: pickleshare
Requires-Dist: optuna
Requires-Dist: plotly
